README.md
setup.py
antchain_alipay_util/__init__.py
antchain_alipay_util/antchain_utils.py
antchain_alipay_util.egg-info/PKG-INFO
antchain_alipay_util.egg-info/SOURCES.txt
antchain_alipay_util.egg-info/dependency_links.txt
antchain_alipay_util.egg-info/top_level.txt